kivy_translate/__init__.py
kivy_translate/kivy_translate.py
kivy_translate/kvtranslate.py
kivy_translate/translate.py
kivy_translate-0.2.0.dist-info/LICENSE.txt
kivy_translate-0.2.0.dist-info/METADATA
kivy_translate-0.2.0.dist-info/WHEEL
kivy_translate-0.2.0.dist-info/entry_points.txt
kivy_translate-0.2.0.dist-info/top_level.txt
kivy_translate-0.2.0.dist-info/RECORD
