Metadata-Version: 2.1
Name: kivy-translate
Version: 0.2.0
Summary: Tool to make translations in kivy a little easier.
Home-page: https://github.com/NomadDemon/kivy_translate
Author: Marcin Drobnik
Author-email: hydra@stacja1.pl
License: MIT
Project-URL: Source, https://github.com/NomadDemon/kivy_translate
Classifier: Development Status :: 4 - Beta
Classifier: Intended Audience :: Developers
Classifier: Topic :: Software Development :: Localization
Classifier: Topic :: Software Development :: Libraries :: Python Modules
Classifier: Programming Language :: Python :: 3
Classifier: Operating System :: OS Independent
Classifier: License :: OSI Approved :: MIT License
Requires-Python: >=3.8
License-File: LICENSE.txt
Requires-Dist: configparser
